transfer/__init__.py
transfer/transfer.py
s3filetransfer-0.1.0.dist-info/LICENSE
s3filetransfer-0.1.0.dist-info/METADATA
s3filetransfer-0.1.0.dist-info/WHEEL
s3filetransfer-0.1.0.dist-info/top_level.txt
s3filetransfer-0.1.0.dist-info/RECORD
